botnoi/__init__.py
botnoi/botnoidict.p
botnoi/botnoigooglesheet.py
botnoi/botnoitfidf_v1.mod
botnoi/botnoiw2v_small.mod
botnoi/chatbot.py
botnoi/credentials.json
botnoi/cv.py
botnoi/decode.py
botnoi/getbow.py
botnoi/getw2v.py
botnoi/googlesheet.py
botnoi/line.py
botnoi/mobilenet.py
botnoi/nlp.py
botnoi/nlpcorrection.py
botnoi/openapi.py
botnoi/resnet50.py
botnoi/scrape.py
botnoi-0.7.6.dist-info/METADATA
botnoi-0.7.6.dist-info/WHEEL
botnoi-0.7.6.dist-info/top_level.txt
botnoi-0.7.6.dist-info/RECORD
