Metadata-Version: 2.1
Name: botnoi
Version: 0.7.6
Summary: BOTNOI
Home-page: https://github.com/winn/botnoi
Author: Winn Voravuthikunchai
Author-email: vwinnv@gmail.com
License: MIT
Download-URL: https://pypi.org/project/botnoinlp/
Keywords: NLP
Platform: UNKNOWN
Requires-Dist: pandas
Requires-Dist: pillow
Requires-Dist: pythainlp
Requires-Dist: gensim
Requires-Dist: pymongo[srv,tls]
Requires-Dist: SpeechRecognition
Requires-Dist: wave
Requires-Dist: audioread
Requires-Dist: line-bot-sdk
Requires-Dist: gspread (==3.6.0)
Requires-Dist: scikit-learn
Requires-Dist: boto
Requires-Dist: boto3
Requires-Dist: facebook-sdk
Requires-Dist: multiprocess
Requires-Dist: tweepy
Requires-Dist: tensorflow (==2.6.0)
Requires-Dist: keras (==2.6.0)
